extract_bib/__init__.py
tests/__init__.py
tests/test_extract_bib.py
extract_bib-1.0.0.dist-info/LICENSE
extract_bib-1.0.0.dist-info/METADATA
extract_bib-1.0.0.dist-info/WHEEL
extract_bib-1.0.0.dist-info/entry_points.txt
extract_bib-1.0.0.dist-info/top_level.txt
extract_bib-1.0.0.dist-info/RECORD
