Metadata-Version: 2.1
Name: extract-bib
Version: 1.0.0
Summary: A small utility that uses BibTool to extract the references used in a Pandoc Markdown file.
Home-page: https://github.com/willbarton/extract_bib
Author: Will Barton
Author-email: will@brtns.com
License: MIT
Platform: UNKNOWN
Classifier: Programming Language :: Python :: 3
Classifier: License :: OSI Approved :: MIT License
Classifier: Operating System :: OS Independent
Provides-Extra: testing
Requires-Dist: black ; extra == 'testing'
Requires-Dist: check-manifest ; extra == 'testing'
Requires-Dist: coverage ; extra == 'testing'
Requires-Dist: flake8 ; extra == 'testing'
Requires-Dist: pytest ; extra == 'testing'
